nhi/__init__.py
nhi/_nhi.py
python_nhi-1.2.2.dist-info/licenses/LICENSE
python_nhi-1.2.2.dist-info/METADATA
python_nhi-1.2.2.dist-info/WHEEL
python_nhi-1.2.2.dist-info/top_level.txt
python_nhi-1.2.2.dist-info/RECORD
