Metadata-Version: 2.4
Name: python-nhi
Version: 1.2.2
Summary: A function to check strings against the New Zealand Ministry of Health NHI Validation Routine
License-Expression: Apache-2.0
Project-URL: repository, https://codeberg.org/jamesansley/nhi
Requires-Python: >=3.9
License-File: LICENSE
Dynamic: license-file
